{
  "resourceType": "NamingSystem",
  "id": "hpiOrganization",
  "name": "HPIOrganization",
  "description": "HPI organizations",
  "status": "active",
  "kind": "identifier",
  "date": "2020-07-14",
  "responsible": "HISO",
  "uniqueId": [
    {
      "type": "uri",
      "value": "https://standards.digital.health.nz/ns/hpi-organisation-id",
      "preferred": true
    },
    {
      "type": "uri",
      "value": "https://standards.digital.health.nz/id/hpi-organisation",
      "comment": "Deprecated"
    }
  ]
}
